Workbook

Sheet README
A1: Care Data Services — Multi-Facility Tracker
A3: Purpose | B3: Track support plan renewals, DoLS authorisations, and facility expenses across all sites. Feed into Power BI for live dashboards.
A5: Sheet | B5: What to fill in
A6: Facilities | B6: Add one row per facility. Must be completed first — other sheets reference this list.
A7: Clients | B7: One row per client across all facilities. Enter key dates and funding details.
A8: Support Plans | B8: One row per support plan. Enter review dates — traffic lights update automatically.
A9: DoLS | B9: One row per DoLS authorisation. Enter grant and expiry dates — alerts auto-calculate.
A10: Expenses | B10: One row per expense line per facility per month.
A11: Summary | B11: Do not edit — auto-calculated from other sheets. Used by Power BI.
A13: Rules
A14: Date format | B14: Always enter dates as DD/MM/YYYY. The cells are pre-formatted.
A15: Client ID | B15: Use the same Client ID across all sheets to link records correctly.
A16: Facility ID | B16: Use the Facility ID from the Facilities sheet exactly as entered.
A17: Status fields | B17: Select from the dropdown lists provided — do not type free text in status columns.
A18: Adding rows | B18: Click the last row of any table and press Tab to add a new row. Do not insert rows above the table.
A19: Power BI | B19: Save this file to a shared OneDrive or SharePoint folder. Power BI connects directly to that location and refreshes automatically.
A21: Colour coding
A22: Green | B22: On track — no action needed.
A23: Amber | B23: Due within 30 days — plan renewal now.
A24: Red | B24: Overdue or expires within 14 days — immediate action required.

Sheet Facilities
A1: Facilities
A2: One row per facility — complete this sheet first
A3: Facility ID | B3: Facility Name | C3: Address | D3: Borough | E3: Registered Manager | F3: Manager Email | G3: Manager Phone | H3: CQC Number | I3: Registered Beds | J3: Current Occupancy | K3: Facility Type | L3: Date Opened | M3: Active
A4: FAC-001 | B4: Market Street | C4: 152 Market Street, East Ham, E6 2PU | D4: Newham | E4: Grace Antwi-Nyame | F4: ebenezerrch@gmail.com | G4: 7908661708 | H4: 1-12345001 | I4: 5 | J4: 5 | K4: Residential | L4: 01/04/2015 | M4: Yes
A5: FAC-002 | B5: 404 Romford Road | C5: 404 Romford Road, Forest Gate, E7 8DF | D5: Newham | E5: Grace Antwi-Nyame | F5: ebenezerrch@gmail.com | G5: 7908661708 | H5: 1-12345002 | I5: 5 | J5: 5 | K5: Residential | L5: 15/09/2018 | M5: Yes
A6: FAC-003 | B6: Thorngrove Lodge | C6: 29 Thorngrove Lodge, Newham, E13 0SH | D6: Newham | E6: Grace Antwi-Nyame | F6: ebenezerrch@gmail.com | G6: 7908661708 | H6: 1-12345003 | I6: 5 | J6: 5 | K6: Residential | L6: 03/06/2020 | M6: Yes
A7: FAC-004 | B7: St. Stephens Lodge | C7: 25 St. Stephens Road, Newham, E6 1AN | D7: Newham | E7: Grace Antwi-Nyame | F7: ebenezerrch@gmail.com | G7: 7908661708 | I7: 5 | J7: 5 | K7: Residential | M7: Yes
A8: FAC-005 | B8: 167 High Street South | C8: 167 High Street South, Newham, E6 3PA | D8: Newham | E8: Grace Antwi-Nyame | F8: ebenezerrch@gmail.com | G8: 7908661708 | I8: 5 | J8: 5 | K8: Residential | M8: Yes
A9: FAC-006 | B9: 9A Napier Road | C9: 9A Napier Road, Waltham Forest, E11 3JJ | D9: Newham | E9: Grace Antwi-Nyame | F9: ebenezerrch@gmail.com | G9: 7908661708 | I9: 5 | J9: 5 | K9: Residential | M9: Yes
A10: FAC-007 | B10: Bank Avenue | C10: 17 Bank Avenue, Mitcham, CR4 3DW | D10: Newham | E10: Grace Antwi-Nyame | F10: ebenezerrch@gmail.com | G10: 7908661708 | I10: 5 | J10: 5 | K10: Residential | M10: Yes
A11: FAC-008 | B11: Sherwood Park | C11: 70 Sherwood Park Avenue | D11: Merton | E11: Grace Antwi-Nyame | F11: ebenezerrch@gmail.com | G11: 7908661708 | I11: 5 | J11: 5 | K11: Residential | M11: Yes

Sheet Clients
A1: Clients
A2: One row per client — use the same Client ID across all sheets
A3: Client ID | B3: Client Initials | C3: Facility ID | D3: Facility Name | E3: Date of Birth | F3: Age | G3: Admission Date | H3: Gender | I3: Primary Diagnosis | J3: Funding Type | K3: Weekly Fee (£) | L3: Local Authority | M3: NHS CHC | N3: Active | O3: Notes
A4: CLI-001 | B4: Burton Albert Grant | C4: FAC-001 | D4: =IFERROR(INDEX(Facilities!B:B,MATCH(C4,Facilities!A:A,0)),"") -> Market Street | E4: 21048 | F4: =IFERROR(DATEDIF(E4,TODAY(),"Y"),"") -> 68 | G4: 12/01/2024 | H4: F | I4: Paranoid Schizophrenia | J4: Local Authority | K4: 1200 | L4: Newham Borough | M4: No | N4: Yes
A5: CLI-002 | B5: Sangana Rana | C5: FAC-001 | D5: =IFERROR(INDEX(Facilities!B:B,MATCH(C5,Facilities!A:A,0)),"") -> Market Street | E5: 24998 | F5: =IFERROR(DATEDIF(E5,TODAY(),"Y"),"") -> 57 | G5: 03/06/2023 | H5: M | I5: Paranoid Schizophrenia | J5: Local Authority | K5: 1650 | L5: Newham Borough | M5: No | N5: Yes
A6: CLI-003 | B6: Francisco Victoriano | C6: FAC-001 | D6: =IFERROR(INDEX(Facilities!B:B,MATCH(C6,Facilities!A:A,0)),"") -> Market Street | E6: 27127 | F6: =IFERROR(DATEDIF(E6,TODAY(),"Y"),"") -> 52 | G6: 19/09/2024 | H6: F | I6: Paranoid Schizophrenia | J6: Local Authority | K6: 0 | L6: Newham Borough | M6: Yes | N6: Yes
A7: CLI-004 | B7: Emmanuel Brown | C7: FAC-001 | D7: =IFERROR(INDEX(Facilities!B:B,MATCH(C7,Facilities!A:A,0)),"") -> Market Street | E7: 27513 | F7: =IFERROR(DATEDIF(E7,TODAY(),"Y"),"") -> 51 | G7: 07/02/2025 | H7: M | I7: Paranoid Schizophrenia | J7: Local Authority | K7: 1100 | L7: Newham Borough | M7: No | N7: Yes
A8: CLI-005 | B8: Christine Ann Philips | C8: FAC-002 | D8: =IFERROR(INDEX(Facilities!B:B,MATCH(C8,Facilities!A:A,0)),"") -> 404 Romford Road | E8: 18108 | F8: =IFERROR(DATEDIF(E8,TODAY(),"Y"),"") -> 76 | H8: F | I8: Paranoid Schizophrenia | J8: Local Authority | L8: Newham Borough | N8: Yes
A9: CLI-006 | B9: David Alexander John Gourlay | C9: FAC-002 | D9: =IFERROR(INDEX(Facilities!B:B,MATCH(C9,Facilities!A:A,0)),"") -> 404 Romford Road | E9: 30429 | F9: =IFERROR(DATEDIF(E9,TODAY(),"Y"),"") -> 43 | H9: M | I9: Paranoid Schizophrenia | J9: Local Authority | L9: Newham Borough | N9: Yes
A10: CLI-007 | B10: Irene Henshaw | C10: FAC-002 | D10: =IFERROR(INDEX(Facilities!B:B,MATCH(C10,Facilities!A:A,0)),"") -> 404 Romford Road | E10: 26054 | F10: =IFERROR(DATEDIF(E10,TODAY(),"Y"),"") -> 55 | H10: F | I10: Paranoid Schizophrenia | J10: Local Authority | L10: Newham Borough | N10: Yes
A11: CLI-008 | B11: Kanthan Rentirakumar | C11: FAC-002 | D11: =IFERROR(INDEX(Facilities!B:B,MATCH(C11,Facilities!A:A,0)),"") -> 404 Romford Road | E11: 24859 | F11: =IFERROR(DATEDIF(E11,TODAY(),"Y"),"") -> 58 | H11: M | I11: Paranoid Schizophrenia | J11: Local Authority | L11: Newham Borough | N11: Yes
A12: CLI-009 | B12: Theresa Thompson | C12: FAC-002 | D12: =IFERROR(INDEX(Facilities!B:B,MATCH(C12,Facilities!A:A,0)),"") -> 404 Romford Road | E12: 22991 | F12: =IFERROR(DATEDIF(E12,TODAY(),"Y"),"") -> 63 | H12: F | I12: Paranoid Schizophrenia | J12: Local Authority | L12: Newham Borough | N12: Yes
A13: CLI-010 | B13: Anthony Pile Mark | C13: FAC-003 | D13: =IFERROR(INDEX(Facilities!B:B,MATCH(C13,Facilities!A:A,0)),"") -> Thorngrove Lodge | E13: 27305 | F13: =IFERROR(DATEDIF(E13,TODAY(),"Y"),"") -> 51 | H13: M | I13: Paranoid Schizophrenia | J13: Local Authority | L13: Newham Borough | N13: Yes
A14: CLI-011 | B14: Peter Antonio | C14: FAC-003 | D14: =IFERROR(INDEX(Facilities!B:B,MATCH(C14,Facilities!A:A,0)),"") -> Thorngrove Lodge | E14: 24772 | F14: =IFERROR(DATEDIF(E14,TODAY(),"Y"),"") -> 58 | H14: M | I14: Paranoid Schizophrenia | J14: Local Authority | L14: Newham Borough | N14: Yes
A15: CLI-012 | B15: Wayne Smikley | C15: FAC-003 | D15: =IFERROR(INDEX(Facilities!B:B,MATCH(C15,Facilities!A:A,0)),"") -> Thorngrove Lodge | E15: 28165 | F15: =IFERROR(DATEDIF(E15,TODAY(),"Y"),"") -> 49 | H15: M | I15: Paranoid Schizophrenia | J15: Local Authority | L15: Newham Borough | N15: Yes
A16: CLI-013 | B16: Maria Fitzgerald | C16: FAC-003 | D16: =IFERROR(INDEX(Facilities!B:B,MATCH(C16,Facilities!A:A,0)),"") -> Thorngrove Lodge | E16: 23816 | F16: =IFERROR(DATEDIF(E16,TODAY(),"Y"),"") -> 61 | H16: F | I16: Paranoid Schizophrenia | J16: Local Authority | L16: Newham Borough | N16: Yes
A17: CLI-014 | B17: Carrick Joanne May | C17: FAC-004 | D17: =IFERROR(INDEX(Facilities!B:B,MATCH(C17,Facilities!A:A,0)),"") -> St. Stephens Lodge | E17: 25771 | F17: =IFERROR(DATEDIF(E17,TODAY(),"Y"),"") -> 55 | H17: F | I17: Paranoid Schizophrenia | J17: Local Authority | L17: Newham Borough | N17: Yes
A18: CLI-015 | B18: Gordon Jason Stuart | C18: FAC-004 | D18: =IFERROR(INDEX(Facilities!B:B,MATCH(C18,Facilities!A:A,0)),"") -> St. Stephens Lodge | E18: 25324 | F18: =IFERROR(DATEDIF(E18,TODAY(),"Y"),"") -> 57 | H18: M | I18: Paranoid Schizophrenia | J18: Local Authority | L18: Newham Borough | N18: Yes
A19: CLI-016 | B19: Thomas Ansere | C19: FAC-004 | D19: =IFERROR(INDEX(Facilities!B:B,MATCH(C19,Facilities!A:A,0)),"") -> St. Stephens Lodge | E19: 25741 | F19: =IFERROR(DATEDIF(E19,TODAY(),"Y"),"") -> 55 | H19: M | I19: Paranoid Schizophrenia | J19: Local Authority | L19: Newham Borough | N19: Yes
... A29: CLI-026 | B29: Kenya Lendo | C29: FAC-006 | D29: =IFERROR(INDEX(Facilities!B:B,MATCH(C29,Facilities!A:A,0)),"") -> 9A Napier Road | E29: 36929 | F29: =IFERROR(DATEDIF(E29,TODAY(),"Y"),"") -> 25 | H29: F | I29: Paranoid Schizophrenia | J29: Local Authority | L29: Newham Borough | N29: Yes

Sheet Support Plans
A1: Support Plans
A2: One row per support plan — traffic lights update automatically
A3: Record ID | B3: Client ID | C3: Client Initials | D3: Facility ID | E3: Plan Type | F3: Plan Start Date | G3: Last Review Date | H3: Next Review Due | I3: Days Until Due | J3: Renewal Status | K3: Assigned Key Worker | L3: Review Completed | M3: Notes
A4: SP-001 | B4: CLI-001 | C4: Burton Albert Grant | D4: FAC-001 | E4: Person-centred plan | F4: 01/04/2024 | G4: 46114 | H4: 46205 | I4: =IFERROR(H4-TODAY(),"") -> 60 | J4: =IFERROR(IF(H4="","",IF(H4<TODAY(),"OVERDUE",IF(H4-TODAY()<=14,"Expires in 14 days",IF(H4-TODAY()<=30,"Due within 30 days","On track")))),"On track") -> On track | K4: Key Worker 1 | L4: Yes
A5: SP-002 | B5: CLI-002 | C5: Sangana Rana | D5: FAC-001 | E5: Person-centred plan | F5: 01/04/2024 | G5: 46114 | H5: 46205 | I5: =IFERROR(H5-TODAY(),"") -> 60 | J5: =IFERROR(IF(H5="","",IF(H5<TODAY(),"OVERDUE",IF(H5-TODAY()<=14,"Expires in 14 days",IF(H5-TODAY()<=30,"Due within 30 days","On track")))),"On track") -> On track | K5: Key Worker 1 | L5: Yes | M5: Overdue — contact manager
A6: SP-003 | B6: CLI-003 | C6: Francisco Victoriano | D6: FAC-001 | E6: Person-centred plan | F6: 01/04/2024 | G6: 46114 | H6: 46205 | I6: =IFERROR(H6-TODAY(),"") -> 60 | J6: =IFERROR(IF(H6="","",IF(H6<TODAY(),"OVERDUE",IF(H6-TODAY()<=14,"Expires in 14 days",IF(H6-TODAY()<=30,"Due within 30 days","On track")))),"On track") -> On track | K6: Key Worker 2 | L6: Yes
A7: SP-004 | B7: CLI-004 | C7: Emmanuel Brown | D7: FAC-001 | E7: Person-centred plan | F7: 01/04/2024 | G7: 46114 | H7: 46205 | I7: =IFERROR(H7-TODAY(),"") -> 60 | J7: =IFERROR(IF(H7="","",IF(H7<TODAY(),"OVERDUE",IF(H7-TODAY()<=14,"Expires in 14 days",IF(H7-TODAY()<=30,"Due within 30 days","On track")))),"On track") -> On track | K7: Key Worker 3 | L7: Yes
A8: SP-005 | B8: CLI-005 | C8: Christine Ann Philips | D8: FAC-002 | E8: Person-centred plan | F8: 01/04/2024 | G8: 46114 | H8: 46205 | I8: =IFERROR(H8-TODAY(),"") -> 60 | J8: =IFERROR(IF(H8="","",IF(H8<TODAY(),"OVERDUE",IF(H8-TODAY()<=14,"Expires in 14 days",IF(H8-TODAY()<=30,"Due within 30 days","On track")))),"On track") -> On track | K8: Key Worker 4 | L8: Yes
A9: SP-006 | B9: CLI-006 | C9: David Alexander John Gourlay | D9: FAC-002 | E9: Person-centred plan | F9: 01/04/2024 | G9: 46114 | H9: 46205 | I9: =IFERROR(H9-TODAY(),"") -> 60 | J9: =IFERROR(IF(H9="","",IF(H9<TODAY(),"OVERDUE",IF(H9-TODAY()<=14,"Expires in 14 days",IF(H9-TODAY()<=30,"Due within 30 days","On track")))),"On track") -> On track | K9: Key Worker 5 | L9: Yes
A10: SP-007 | B10: CLI-007 | C10: Irene Henshaw | D10: FAC-002 | E10: Person-centred plan | F10: 01/04/2024 | G10: 46114 | H10: 46205 | I10: =IFERROR(H10-TODAY(),"") -> 60 | J10: =IFERROR(IF(H10="","",IF(H10<TODAY(),"OVERDUE",IF(H10-TODAY()<=14,"Expires in 14 days",IF(H10-TODAY()<=30,"Due within 30 days","On track")))),"On track") -> On track | K10: Key Worker 6 | L10: Yes
A11: SP-008 | B11: CLI-008 | C11: Kanthan Rentirakumar | D11: FAC-002 | E11: Person-centred plan | F11: 01/04/2024 | G11: 46114 | H11: 46205 | I11: =IFERROR(H11-TODAY(),"") -> 60 | J11: =IFERROR(IF(H11="","",IF(H11<TODAY(),"OVERDUE",IF(H11-TODAY()<=14,"Expires in 14 days",IF(H11-TODAY()<=30,"Due within 30 days","On track")))),"On track") -> On track | K11: Key Worker 7 | L11: Yes
A12: SP-009 | B12: CLI-009 | C12: Theresa Thompson | D12: FAC-002 | E12: Person-centred plan | F12: 01/04/2024 | G12: 46114 | H12: 46205 | I12: =IFERROR(H12-TODAY(),"") -> 60 | J12: =IFERROR(IF(H12="","",IF(H12<TODAY(),"OVERDUE",IF(H12-TODAY()<=14,"Expires in 14 days",IF(H12-TODAY()<=30,"Due within 30 days","On track")))),"On track") -> On track | K12: Key Worker 8 | L12: Yes
A13: SP-010 | B13: CLI-010 | C13: Anthony Pile Mark | D13: FAC-003 | E13: Person-centred plan | F13: 01/04/2024 | G13: 46114 | H13: 46205 | I13: =IFERROR(H13-TODAY(),"") -> 60 | J13: =IFERROR(IF(H13="","",IF(H13<TODAY(),"OVERDUE",IF(H13-TODAY()<=14,"Expires in 14 days",IF(H13-TODAY()<=30,"Due within 30 days","On track")))),"On track") -> On track | K13: Key Worker 9 | L13: Yes
A14: SP-011 | B14: CLI-011 | C14: Peter Antonio | D14: FAC-003 | E14: Person-centred plan | F14: 01/04/2024 | G14: 46114 | H14: 46205 | I14: =IFERROR(H14-TODAY(),"") -> 60 | J14: =IFERROR(IF(H14="","",IF(H14<TODAY(),"OVERDUE",IF(H14-TODAY()<=14,"Expires in 14 days",IF(H14-TODAY()<=30,"Due within 30 days","On track")))),"On track") -> On track | K14: Key Worker 10 | L14: Yes
A15: SP-012 | B15: CLI-012 | C15: Wayne Smikley | D15: FAC-003 | E15: Person-centred plan | F15: 01/04/2024 | G15: 46114 | H15: 46205 | I15: =IFERROR(H15-TODAY(),"") -> 60 | J15: =IFERROR(IF(H15="","",IF(H15<TODAY(),"OVERDUE",IF(H15-TODAY()<=14,"Expires in 14 days",IF(H15-TODAY()<=30,"Due within 30 days","On track")))),"On track") -> On track | K15: Key Worker 11 | L15: Yes
A16: SP-013 | B16: CLI-013 | C16: Maria Fitzgerald | D16: FAC-003 | E16: Person-centred plan | F16: 01/04/2024 | G16: 46114 | H16: 46205 | I16: =IFERROR(H16-TODAY(),"") -> 60 | J16: =IFERROR(IF(H16="","",IF(H16<TODAY(),"OVERDUE",IF(H16-TODAY()<=14,"Expires in 14 days",IF(H16-TODAY()<=30,"Due within 30 days","On track")))),"On track") -> On track | K16: Key Worker 12 | L16: Yes
A17: SP-014 | B17: CLI-014 | C17: Carrick Joanne May | D17: FAC-004 | E17: Person-centred plan | F17: 07/02/2034 | G17: 46100 | H17: 46241 | I17: =IFERROR(H17-TODAY(),"") -> 96 | J17: =IFERROR(IF(H17="","",IF(H17<TODAY(),"OVERDUE",IF(H17-TODAY()<=14,"Expires in 14 days",IF(H17-TODAY()<=30,"Due within 30 days","On track")))),"On track") -> On track | K17: Key Worker 13 | L17: No
... A42: SP-013 | B42: CLI-026 | C42: Kenya Lendo | D42: FAC-006 | E42: Person-centred plan | F42: 01/04/2024 | G42: 46114 | H42: 46205 | I42: =IFERROR(H42-TODAY(),"") -> 60 | J42: =IFERROR(IF(H42="","",IF(H42<TODAY(),"OVERDUE",IF(H42-TODAY()<=14,"Expires in 14 days",IF(H42-TODAY()<=30,"Due within 30 days","On track")))),"On track") -> On track | K42: Key Worker 12 | L42: Yes
J43: =IFERROR(IF(H43="","",IF(H43<TODAY(),"OVERDUE",IF(H43-TODAY()<=14,"Expires in 14 days",IF(H43-TODAY()<=30,"Due within 30 days","On track")))),"On track")
J44: =IFERROR(IF(H44="","",IF(H44<TODAY(),"OVERDUE",IF(H44-TODAY()<=14,"Expires in 14 days",IF(H44-TODAY()<=30,"Due within 30 days","On track")))),"On track")
J45: =IFERROR(IF(H45="","",IF(H45<TODAY(),"OVERDUE",IF(H45-TODAY()<=14,"Expires in 14 days",IF(H45-TODAY()<=30,"Due within 30 days","On track")))),"On track")
J46: =IFERROR(IF(H46="","",IF(H46<TODAY(),"OVERDUE",IF(H46-TODAY()<=14,"Expires in 14 days",IF(H46-TODAY()<=30,"Due within 30 days","On track")))),"On track")
J47: =IFERROR(IF(H47="","",IF(H47<TODAY(),"OVERDUE",IF(H47-TODAY()<=14,"Expires in 14 days",IF(H47-TODAY()<=30,"Due within 30 days","On track")))),"On track")
J48: =IFERROR(IF(H48="","",IF(H48<TODAY(),"OVERDUE",IF(H48-TODAY()<=14,"Expires in 14 days",IF(H48-TODAY()<=30,"Due within 30 days","On track")))),"On track")
J49: =IFERROR(IF(H49="","",IF(H49<TODAY(),"OVERDUE",IF(H49-TODAY()<=14,"Expires in 14 days",IF(H49-TODAY()<=30,"Due within 30 days","On track")))),"On track")
J50: =IFERROR(IF(H50="","",IF(H50<TODAY(),"OVERDUE",IF(H50-TODAY()<=14,"Expires in 14 days",IF(H50-TODAY()<=30,"Due within 30 days","On track")))),"On track")
J51: =IFERROR(IF(H51="","",IF(H51<TODAY(),"OVERDUE",IF(H51-TODAY()<=14,"Expires in 14 days",IF(H51-TODAY()<=30,"Due within 30 days","On track")))),"On track")
J52: =IFERROR(IF(H52="","",IF(H52<TODAY(),"OVERDUE",IF(H52-TODAY()<=14,"Expires in 14 days",IF(H52-TODAY()<=30,"Due within 30 days","On track")))),"On track")
J53: =IFERROR(IF(H53="","",IF(H53<TODAY(),"OVERDUE",IF(H53-TODAY()<=14,"Expires in 14 days",IF(H53-TODAY()<=30,"Due within 30 days","On track")))),"On track")
J54: =IFERROR(IF(H54="","",IF(H54<TODAY(),"OVERDUE",IF(H54-TODAY()<=14,"Expires in 14 days",IF(H54-TODAY()<=30,"Due within 30 days","On track")))),"On track")
... J161: =IFERROR(IF(H161="","",IF(H161<TODAY(),"OVERDUE",IF(H161-TODAY()<=14,"Expires in 14 days",IF(H161-TODAY()<=30,"Due within 30 days","On track")))),"On track")

Sheet DoLS
A1: DoLS — Deprivation of Liberty Safeguards
A2: Track authorisation and expiry dates — red alerts fire automatically
A3: Record ID | B3: Client ID | C3: Client Initials | D3: Facility ID | E3: Date Applied | F3: Date Granted | G3: Expiry Date | H3: Days Until Expiry | I3: DoLS Status | J3: Authorised By | K3: Conditions | L3: Renewal Applied | M3: Notes
A4: DOL-001 | B4: CLI-001 | C4: =IFERROR(INDEX(Clients!B:B,MATCH(B4,Clients!A:A,0)),"") -> Burton Albert Grant | D4: FAC-001 | E4: 46054 | F4: 46063 | G4: 46428 | H4: =IFERROR(IF(G4="","",G4-TODAY()),"") -> 283 | I4: =IFERROR(IF(G4="","Not yet granted",IF(G4<TODAY(),"EXPIRED",IF(G4-TODAY()<=14,"Expires in 14 days",IF(G4-TODAY()<=30,"Review within 30 days","Active")))),"Not yet granted") -> Active | J4: DOLS Team | K4: Conditions apply | L4: Yes | M4: Standard auth
A5: DOL-002 | B5: CLI-002 | C5: Sangana Rana | D5: FAC-001 | E5: 46055 | F5: 46065 | G5: 46430 | H5: =IFERROR(IF(G5="","",G5-TODAY()),"") -> 285 | I5: =IFERROR(IF(G5="","Not yet granted",IF(G5<TODAY(),"EXPIRED",IF(G5-TODAY()<=14,"Expires in 14 days",IF(G5-TODAY()<=30,"Review within 30 days","Active")))),"Not yet granted") -> Active | J5: DOLS Team | K5: Conditions apply | L5: Yes | M5: Standard auth
H6: =IFERROR(IF(G6="","",G6-TODAY()),"") | I6: =IFERROR(IF(G6="","Not yet granted",IF(G6<TODAY(),"EXPIRED",IF(G6-TODAY()<=14,"Expires in 14 days",IF(G6-TODAY()<=30,"Review within 30 days","Active")))),"Not yet granted") -> Not yet granted
H7: =IFERROR(IF(G7="","",G7-TODAY()),"") | I7: =IFERROR(IF(G7="","Not yet granted",IF(G7<TODAY(),"EXPIRED",IF(G7-TODAY()<=14,"Expires in 14 days",IF(G7-TODAY()<=30,"Review within 30 days","Active")))),"Not yet granted") -> Not yet granted
H8: =IFERROR(IF(G8="","",G8-TODAY()),"") | I8: =IFERROR(IF(G8="","Not yet granted",IF(G8<TODAY(),"EXPIRED",IF(G8-TODAY()<=14,"Expires in 14 days",IF(G8-TODAY()<=30,"Review within 30 days","Active")))),"Not yet granted") -> Not yet granted
H9: =IFERROR(IF(G9="","",G9-TODAY()),"") | I9: =IFERROR(IF(G9="","Not yet granted",IF(G9<TODAY(),"EXPIRED",IF(G9-TODAY()<=14,"Expires in 14 days",IF(G9-TODAY()<=30,"Review within 30 days","Active")))),"Not yet granted") -> Not yet granted
H10: =IFERROR(IF(G10="","",G10-TODAY()),"") | I10: =IFERROR(IF(G10="","Not yet granted",IF(G10<TODAY(),"EXPIRED",IF(G10-TODAY()<=14,"Expires in 14 days",IF(G10-TODAY()<=30,"Review within 30 days","Active")))),"Not yet granted") -> Not yet granted
H11: =IFERROR(IF(G11="","",G11-TODAY()),"") | I11: =IFERROR(IF(G11="","Not yet granted",IF(G11<TODAY(),"EXPIRED",IF(G11-TODAY()<=14,"Expires in 14 days",IF(G11-TODAY()<=30,"Review within 30 days","Active")))),"Not yet granted") -> Not yet granted
H12: =IFERROR(IF(G12="","",G12-TODAY()),"") | I12: =IFERROR(IF(G12="","Not yet granted",IF(G12<TODAY(),"EXPIRED",IF(G12-TODAY()<=14,"Expires in 14 days",IF(G12-TODAY()<=30,"Review within 30 days","Active")))),"Not yet granted") -> Not yet granted
H13: =IFERROR(IF(G13="","",G13-TODAY()),"") | I13: =IFERROR(IF(G13="","Not yet granted",IF(G13<TODAY(),"EXPIRED",IF(G13-TODAY()<=14,"Expires in 14 days",IF(G13-TODAY()<=30,"Review within 30 days","Active")))),"Not yet granted") -> Not yet granted
H14: =IFERROR(IF(G14="","",G14-TODAY()),"") | I14: =IFERROR(IF(G14="","Not yet granted",IF(G14<TODAY(),"EXPIRED",IF(G14-TODAY()<=14,"Expires in 14 days",IF(G14-TODAY()<=30,"Review within 30 days","Active")))),"Not yet granted") -> Not yet granted
H15: =IFERROR(IF(G15="","",G15-TODAY()),"") | I15: =IFERROR(IF(G15="","Not yet granted",IF(G15<TODAY(),"EXPIRED",IF(G15-TODAY()<=14,"Expires in 14 days",IF(G15-TODAY()<=30,"Review within 30 days","Active")))),"Not yet granted") -> Not yet granted
H16: =IFERROR(IF(G16="","",G16-TODAY()),"") | I16: =IFERROR(IF(G16="","Not yet granted",IF(G16<TODAY(),"EXPIRED",IF(G16-TODAY()<=14,"Expires in 14 days",IF(G16-TODAY()<=30,"Review within 30 days","Active")))),"Not yet granted") -> Not yet granted
H17: =IFERROR(IF(G17="","",G17-TODAY()),"") | I17: =IFERROR(IF(G17="","Not yet granted",IF(G17<TODAY(),"EXPIRED",IF(G17-TODAY()<=14,"Expires in 14 days",IF(G17-TODAY()<=30,"Review within 30 days","Active")))),"Not yet granted") -> Not yet granted
... H202: =IFERROR(IF(G202="","",G202-TODAY()),"") | I202: =IFERROR(IF(G202="","Not yet granted",IF(G202<TODAY(),"EXPIRED",IF(G202-TODAY()<=14,"Expires in 14 days",IF(G202-TODAY()<=30,"Review within 30 days","Active")))),"Not yet granted") -> Not yet granted

Sheet Expenses
A1: Expenses
A2: One row per expense line — enter month and facility for each entry
A3: Record ID | B3: Facility ID | C3: Facility Name | D3: Month | E3: Year | F3: Category | G3: Description | H3: Supplier | I3: Invoice Ref | J3: Amount (£) | K3: VAT (£) | L3: Total (£) | M3: Approved By | N3: Notes
A4: EXP-001 | B4: FAC-001 | C4: =IFERROR(INDEX(Facilities!B:B,MATCH(B4,Facilities!A:A,0)),"") -> Market Street | D4: January | E4: 2025 | F4: Gas | G4: Door handle | H4: BrightAgency | I4: INV-2025-001 | J4: 480 | K4: 96 | L4: =IFERROR(J4+K4,"") -> 576 | M4: EAN
A5: EXP-002 | B5: FAC-001 | C5: =IFERROR(INDEX(Facilities!B:B,MATCH(B5,Facilities!A:A,0)),"") -> Market Street | D5: May | E5: 2025 | F5: Electricity | G5: Gas bill | H5: British Gas | I5: BG-JAN25 | J5: 320 | K5: 64 | L5: =IFERROR(J5+K5,"") -> 384 | M5: GAN
A6: EXP-003 | B6: FAC-002 | C6: =IFERROR(INDEX(Facilities!B:B,MATCH(B6,Facilities!A:A,0)),"") -> 404 Romford Road | D6: January | E6: 2025 | F6: Maintenance | G6: Boiler service | H6: Lewis | I6: HC-0012 | J6: 210 | K6: 42 | L6: =IFERROR(J6+K6,"") -> 252 | M6: ENAN
A7: EXP-004 | B7: FAC-003 | C7: =IFERROR(INDEX(Facilities!B:B,MATCH(B7,Facilities!A:A,0)),"") -> Thorngrove Lodge | D7: September | E7: 2025 | F7: Telephone | G7: Toilet | H7: CareForce | I7: CF-2025-008 | J7: 560 | K7: 112 | L7: =IFERROR(J7+K7,"") -> 672 | M7: JAN
A8: EXP-005 | B8: FAC-001 | C8: =IFERROR(INDEX(Facilities!B:B,MATCH(B8,Facilities!A:A,0)),"") -> Market Street | D8: July | E8: 2025 | F8: Council Tax | G8: Incontinence supplies | H8: Amazon | I8: MS-FEB25 | J8: 145 | K8: 29 | L8: =IFERROR(J8+K8,"") -> 174 | M8: EAN
A9: EXP-006 | B9: FAC-002 | C9: =IFERROR(INDEX(Facilities!B:B,MATCH(B9,Facilities!A:A,0)),"") -> 404 Romford Road | D9: February | E9: 2025 | F9: Water | G9: Moving and handling refresh | H9: Care Kills Academy | I9: TC-0022 | J9: 400 | K9: 80 | L9: =IFERROR(J9+K9,"") -> 480 | M9: EAN
A10: EXP-007 | B10: FAC-003 | C10: =IFERROR(INDEX(Facilities!B:B,MATCH(B10,Facilities!A:A,0)),"") -> Thorngrove Lodge | D10: March | E10: 2025 | F10: Internet | G10: Internet | H10: EE | L10: =IFERROR(J10+K10,"") -> 0 | M10: EAN
A11: EXP-008 | B11: FAC-004 | C11: =IFERROR(INDEX(Facilities!B:B,MATCH(B11,Facilities!A:A,0)),"") -> St. Stephens Lodge | D11: April | E11: 2026 | F11: Amazon order | G11: Gloves | L11: =IFERROR(J11+K11,"") -> 0
L12: =IFERROR(J12+K12,"") -> 0
L13: =IFERROR(J13+K13,"") -> 0
L14: =IFERROR(J14+K14,"") -> 0
L15: =IFERROR(J15+K15,"") -> 0
L16: =IFERROR(J16+K16,"") -> 0
L17: =IFERROR(J17+K17,"") -> 0
L18: =IFERROR(J18+K18,"") -> 0
L19: =IFERROR(J19+K19,"") -> 0
L20: =IFERROR(J20+K20,"") -> 0
L21: =IFERROR(J21+K21,"") -> 0
L22: =IFERROR(J22+K22,"") -> 0
L23: =IFERROR(J23+K23,"") -> 0
... L499: =IFERROR(J499+K499,"") -> 0

Sheet Summary
A1: Summary — auto-calculated, do not edit
A3: Support Plans
A4: Metric | B4: FAC-001 | C4: FAC-002 | D4: FAC-003 | E4: Total
A5: Total plans | B5: =COUNTIF('Support Plans'!D:D,"FAC-001") -> 4 | C5: =COUNTIF('Support Plans'!D:D,"FAC-002") -> 5 | D5: =COUNTIF('Support Plans'!D:D,"FAC-003") -> 4 | E5: =SUM(B5:D5) -> 13
A6: On track | B6: =COUNTIFS('Support Plans'!D:D,"FAC-001",'Support Plans'!J:J,"On track") -> 4 | C6: =COUNTIFS('Support Plans'!D:D,"FAC-002",'Support Plans'!J:J,"On track") -> 5 | D6: =COUNTIFS('Support Plans'!D:D,"FAC-003",'Support Plans'!J:J,"On track") -> 4 | E6: =SUM(B6:D6) -> 13
A7: Due within 30d | B7: =COUNTIFS('Support Plans'!D:D,"FAC-001",'Support Plans'!J:J,"Due within 30 days") -> 0 | C7: =COUNTIFS('Support Plans'!D:D,"FAC-002",'Support Plans'!J:J,"Due within 30 days") -> 0 | D7: =COUNTIFS('Support Plans'!D:D,"FAC-003",'Support Plans'!J:J,"Due within 30 days") -> 0 | E7: =SUM(B7:D7) -> 0
A8: Overdue | B8: =COUNTIFS('Support Plans'!D:D,"FAC-001",'Support Plans'!J:J,"OVERDUE") -> 0 | C8: =COUNTIFS('Support Plans'!D:D,"FAC-002",'Support Plans'!J:J,"OVERDUE") -> 0 | D8: =COUNTIFS('Support Plans'!D:D,"FAC-003",'Support Plans'!J:J,"OVERDUE") -> 0 | E8: =SUM(B8:D8) -> 0
A9: DoLS Authorisations
A10: Metric | B10: FAC-001 | C10: FAC-002 | D10: FAC-003 | E10: Total
A11: Active | B11: =COUNTIFS(DoLS!D:D,"FAC-001",DoLS!I:I,"Active") -> 2 | C11: =COUNTIFS(DoLS!D:D,"FAC-002",DoLS!I:I,"Active") -> 0 | D11: =COUNTIFS(DoLS!D:D,"FAC-003",DoLS!I:I,"Active") -> 0 | E11: =SUM(B11:D11) -> 2
A12: Due within 30d | B12: =COUNTIFS(DoLS!D:D,"FAC-001",DoLS!I:I,"Review within 30 days") -> 0 | C12: =COUNTIFS(DoLS!D:D,"FAC-002",DoLS!I:I,"Review within 30 days") -> 0 | D12: =COUNTIFS(DoLS!D:D,"FAC-003",DoLS!I:I,"Review within 30 days") -> 0 | E12: =SUM(B12:D12) -> 0
A13: Expires in 14 days | B13: =COUNTIFS(DoLS!D:D,"FAC-001",DoLS!I:I,"Expires in 14 days") -> 0 | C13: =COUNTIFS(DoLS!D:D,"FAC-002",DoLS!I:I,"Expires in 14 days") -> 0 | D13: =COUNTIFS(DoLS!D:D,"FAC-003",DoLS!I:I,"Expires in 14 days") -> 0 | E13: =SUM(B13:D13) -> 0
A14: Expired | B14: =COUNTIFS(DoLS!D:D,"FAC-001",DoLS!I:I,"EXPIRED") -> 0 | C14: =COUNTIFS(DoLS!D:D,"FAC-002",DoLS!I:I,"EXPIRED") -> 0 | D14: =COUNTIFS(DoLS!D:D,"FAC-003",DoLS!I:I,"EXPIRED") -> 0 | E14: =SUM(B14:D14) -> 0
A15: Expenses (£)
A16: Metric | B16: FAC-001 | C16: FAC-002 | D16: FAC-003 | E16: Total
A17: Total spend (£) | B17: =SUMIF(Expenses!B:B,"FAC-001",Expenses!L:L) -> 1134 | C17: =SUMIF(Expenses!B:B,"FAC-002",Expenses!L:L) -> 732 | D17: =SUMIF(Expenses!B:B,"FAC-003",Expenses!L:L) -> 672 | E17: =SUM(B17:D17) -> 2538
A18: Staffing (£) | B18: =SUMIFS(Expenses!L:L,Expenses!B:B,"FAC-001",Expenses!F:F,"Staffing") -> 0 | C18: =SUMIFS(Expenses!L:L,Expenses!B:B,"FAC-002",Expenses!F:F,"Staffing") -> 0 | D18: =SUMIFS(Expenses!L:L,Expenses!B:B,"FAC-003",Expenses!F:F,"Staffing") -> 0 | E18: =SUM(B18:D18) -> 0
A19: Utilities (£) | B19: =SUMIFS(Expenses!L:L,Expenses!B:B,"FAC-001",Expenses!F:F,"Utilities") -> 0 | C19: =SUMIFS(Expenses!L:L,Expenses!B:B,"FAC-002",Expenses!F:F,"Utilities") -> 0 | D19: =SUMIFS(Expenses!L:L,Expenses!B:B,"FAC-003",Expenses!F:F,"Utilities") -> 0 | E19: =SUM(B19:D19) -> 0
A20: Maintenance (£) | B20: =SUMIFS(Expenses!L:L,Expenses!B:B,"FAC-001",Expenses!F:F,"Maintenance") -> 0 | C20: =SUMIFS(Expenses!L:L,Expenses!B:B,"FAC-002",Expenses!F:F,"Maintenance") -> 252 | D20: =SUMIFS(Expenses!L:L,Expenses!B:B,"FAC-003",Expenses!F:F,"Maintenance") -> 0 | E20: =SUM(B20:D20) -> 252
